mewo_ovhcloud/__init__.py
mewo_ovhcloud/cmd.py
mewo_ovhcloud/lib.py
mewo_ovhcloud-0.4.0.dist-info/METADATA
mewo_ovhcloud-0.4.0.dist-info/WHEEL
mewo_ovhcloud-0.4.0.dist-info/RECORD
