Metadata-Version: 2.4
Name: mewo_ovhcloud
Version: 0.4.0
Summary: 
Author: feluxe
Author-email: felix@meyerwolters.de
Requires-Python: >=3.14,<4.0
Classifier: Programming Language :: Python :: 3
Classifier: Programming Language :: Python :: 3.14
Requires-Dist: cmdi (>=3.0.0,<4.0.0)
Requires-Dist: ovh (>=1.2.0,<2.0.0)
Requires-Dist: pydantic (>=2.12.0,<3.0.0)
Requires-Dist: requests (>=2.32.5,<3.0.0)
Requires-Dist: sty (>=1.0.6,<2.0.0)
